python_run_cmd/__init__.py
python_run_cmd/run_cmd.py
python_run_cmd/run_cmd_async.py
python_run_cmd/run_cmd_stream.py
python_run_cmd-0.1.1.dist-info/entry_points.txt
python_run_cmd-0.1.1.dist-info/LICENSE
python_run_cmd-0.1.1.dist-info/METADATA
python_run_cmd-0.1.1.dist-info/WHEEL
python_run_cmd-0.1.1.dist-info/RECORD
