Metadata-Version: 2.1
Name: python-run-cmd
Version: 0.1.1
Summary: Run a command within python
Home-page: https://github.com/ffreemt/run-cmd
License: MIT
Author: ffreemt
Requires-Python: >=3.8,<4.0
Classifier: License :: OSI Approved :: MIT License
Classifier: Programming Language :: Python :: 3
Classifier: Programming Language :: Python :: 3.8
Classifier: Programming Language :: Python :: 3.9
Classifier: Programming Language :: Python :: 3.10
Classifier: Programming Language :: Python :: 3.11
Classifier: Programming Language :: Python :: 3.12
Requires-Dist: loguru (>=0.7.0,<0.8.0)
Requires-Dist: rich (>=13.6.0,<14.0.0)
Project-URL: Repository, https://github.com/ffreemt/run-cmd
